Workbook

Sheet Online Sales Data
A1: Sales Management System
A3: Transaction ID | B3: Date | C3: Product Category | D3: Product Name | E3: Units Sold | F3: Unit Price | G3: Total Revenue | H3: Region | I3: Payment Method | J3: Month
A4: 10001 | B4: 45292 | C4: Electronics | D4: iPhone 14 Pro | E4: 2 | F4: 999.99 | G4: 1999.98 | H4: North America | I4: Credit Card | J4: =TEXT(B4,"MMMM") -> January
A5: 10002 | B5: 45293 | C5: Home Appliances | D5: Dyson V11 Vacuum | E5: 1 | F5: 499.99 | G5: 499.99 | H5: Europe | I5: PayPal | J5: =TEXT(B5,"MMMM") -> January
A6: 10003 | B6: 45294 | C6: Clothing | D6: Levi's 501 Jeans | E6: 3 | F6: 69.99 | G6: 209.97 | H6: Asia | I6: Debit Card | J6: =TEXT(B6,"MMMM") -> January
A7: 10004 | B7: 45295 | C7: Books | D7: The Da Vinci Code | E7: 4 | F7: 15.99 | G7: 63.96 | H7: North America | I7: Credit Card | J7: =TEXT(B7,"MMMM") -> January
A8: 10005 | B8: 45296 | C8: Beauty Products | D8: Neutrogena Skincare Set | E8: 1 | F8: 89.99 | G8: 89.99 | H8: Europe | I8: PayPal | J8: =TEXT(B8,"MMMM") -> January
A9: 10006 | B9: 45297 | C9: Sports | D9: Wilson Evolution Basketball | E9: 5 | F9: 29.99 | G9: 149.95 | H9: Asia | I9: Credit Card | J9: =TEXT(B9,"MMMM") -> January
A10: 10007 | B10: 45298 | C10: Electronics | D10: MacBook Pro 16-inch | E10: 1 | F10: 2499.99 | G10: 2499.99 | H10: North America | I10: Credit Card | J10: =TEXT(B10,"MMMM") -> January
A11: 10008 | B11: 45299 | C11: Home Appliances | D11: Blueair Classic 480i | E11: 2 | F11: 599.99 | G11: 1199.98 | H11: Europe | I11: PayPal | J11: =TEXT(B11,"MMMM") -> January
A12: 10009 | B12: 45300 | C12: Clothing | D12: Nike Air Force 1 | E12: 6 | F12: 89.99 | G12: 539.94 | H12: Asia | I12: Debit Card | J12: =TEXT(B12,"MMMM") -> January
A13: 10010 | B13: 45301 | C13: Books | D13: Dune by Frank Herbert | E13: 2 | F13: 25.99 | G13: 51.98 | H13: North America | I13: Credit Card | J13: =TEXT(B13,"MMMM") -> January
A14: 10011 | B14: 45302 | C14: Beauty Products | D14: Chanel No. 5 Perfume | E14: 1 | F14: 129.99 | G14: 129.99 | H14: Europe | I14: PayPal | J14: =TEXT(B14,"MMMM") -> January
A15: 10012 | B15: 45303 | C15: Sports | D15: Babolat Pure Drive Tennis Racket | E15: 3 | F15: 199.99 | G15: 599.97 | H15: Asia | I15: Credit Card | J15: =TEXT(B15,"MMMM") -> January
... A102: 10099 | B102: 45390 | C102: Clothing | D102: Gap Essential Crewneck T-Shirt | E102: 6 | F102: 19.99 | G102: 119.94 | H102: Asia | I102: Debit Card | J102: =TEXT(B102,"MMMM") -> April

Sheet Analysis & Dashboard
A1: Metric | B1: Analysis | E1: Category-Wise Sales | J1: Region - Wise Analysis | O1: Payment Method Analysis
A3: Total Revenue | B3: 41183.74 | E3: Product Category | F3: Total Units | G3: Total Revenue | J3: Region | K3: Total Units | L3: Total Revenue | O3: Payment Method | P3: Transactions | Q3: Revenue
A4: Total Units Sold | B4: =SUM('Online Sales Data'!E4:E102) -> 247 | E4: Electronics | F4: =SUMIF('Online Sales Data'!C:C,"Electronics",'Online Sales Data'!E:E) -> 35 | G4: =SUMIF('Online Sales Data'!C:C,"Electronics",'Online Sales Data'!G:G) -> 16299.65 | J4: North America | K4: =SUMIF('Online Sales Data'!$H4:$H102,J4,'Online Sales Data'!$E4:$E102) -> 85 | L4: =SUMIF('Online Sales Data'!$H4:$H102,J4,'Online Sales Data'!$G4:$G102) -> 17329.22 | O4: Credit Card | P4: =COUNTIF('Online Sales Data'!$I4:$I102,"*Credit Card*") -> 49 | Q4: =SUMIF('Online Sales Data'!$I4:$I102,O4,'Online Sales Data'!$G4:$G102) -> 24512.75
A5: Average Unit Price | B5: =AVERAGE('Online Sales Data'!F4:F102) -> 254.59242 | E5: Home Appliances | F5: =SUMIF('Online Sales Data'!C:C,"Home Appliances",'Online Sales Data'!E:E) -> 25 | G5: =SUMIF('Online Sales Data'!C:C,"Home Appliances",'Online Sales Data'!G:G) -> 10629.75 | J5: Europe | K5: =SUMIF('Online Sales Data'!$H5:$H103,J5,'Online Sales Data'!$E5:$E103) -> 44 | L5: =SUMIF('Online Sales Data'!$H5:$H103,J5,'Online Sales Data'!$G5:$G103) -> 12146.68 | O5: PayPal | P5: =COUNTIF('Online Sales Data'!$I:$I,"*paypal*") -> 33 | Q5: =SUMIF('Online Sales Data'!$I5:$I103,O5,'Online Sales Data'!$G5:$G103) -> 12146.68
A6: Total Transactions | B6: =COUNTA('Online Sales Data'!A4:A102) -> 99 | E6: Clothing | F6: =SUMIF('Online Sales Data'!C:C,"Clothing",'Online Sales Data'!E:E) -> 69 | G6: =SUMIF('Online Sales Data'!C:C,"Clothing",'Online Sales Data'!G:G) -> 4524.31 | J6: Asia | K6: =SUMIF('Online Sales Data'!$H6:$H104,J6,'Online Sales Data'!$E6:$E104) -> 118 | L6: =SUMIF('Online Sales Data'!$H6:$H104,J6,'Online Sales Data'!$G6:$G104) -> 11707.84 | O6: Debit Card | P6: =COUNTIF('Online Sales Data'!$I:$I,"*debit Card*") -> 17 | Q6: =SUMIF('Online Sales Data'!$I6:$I104,O6,'Online Sales Data'!$G6:$G104) -> 4524.31
A7: Highest Revenue | B7: =MAX('Online Sales Data'!G4:G102) -> 2599.98 | E7: Books | F7: =SUMIF('Online Sales Data'!C:C,"Books",'Online Sales Data'!E:E) -> 50 | G7: =SUMIF('Online Sales Data'!C:C,"Books",'Online Sales Data'!G:G) -> 1029.57
A8: Lowest Revenue | B8: =MIN('Online Sales Data'!G4:G102) -> 21.98 | E8: Beauty Products | F8: =SUMIF('Online Sales Data'!C:C,"Beauty Products",'Online Sales Data'!E:E) -> 19 | G8: =SUMIF('Online Sales Data'!C:C,"Beauty Products",'Online Sales Data'!G:G) -> 1516.93
E9: Sports | F9: =SUMIF('Online Sales Data'!C:C,"Sports",'Online Sales Data'!E:E) -> 49 | G9: =SUMIF('Online Sales Data'!C:C,"Sports",'Online Sales Data'!G:G) -> 7183.53
